[
  {
    "address": "951 Brentwood St, Denver, CO",
    "price": 1500.0,
    "beds": 2.0,
    "baths": 1.0,
    "sqft": 750.0,
    "year_built": "N/A",
    "description": "",
    "url": "https://www.zillow.com/homedetails/446860544_zpid/",
    "location": "Denver, CO",
    "list_date": 445155000,
    "primary_photo": "https://photos.zillowstatic.com/fp/cb586fd5b1172c64a847fb722ced6f49-p_e.jpg",
    "alt_photos": [],
    "latitude": 39.731853,
    "longitude": -105.09002
  },
  {
    "address": "1985 Ingalls St, Lakewood, CO",
    "price": 2595.0,
    "beds": 3.0,
    "baths": 2.0,
    "sqft": 864.0,
    "year_built": "N/A",
    "description": "",
    "url": "https://www.zillow.com/homedetails/13749692_zpid/",
    "location": "Lakewood, CO",
    "list_date": 755883000,
    "primary_photo": "https://photos.zillowstatic.com/fp/8fda69547c48e306992fea749abc368f-p_e.jpg",
    "alt_photos": [],
    "latitude": 39.74711,
    "longitude": -105.06418
  },
  {
    "address": "1880 S Cole St UNIT B3, Lakewood, CO",
    "price": 2300.0,
    "beds": 2.0,
    "baths": 3.0,
    "sqft": 1057.0,
    "year_built": "N/A",
    "description": "",
    "url": "https://www.zillow.com/homedetails/51407765_zpid/",
    "location": "Lakewood, CO",
    "list_date": 641814000,
    "primary_photo": "https://photos.zillowstatic.com/fp/46e63e37a60e9f9da94008cceffa5e21-p_e.jpg",
    "alt_photos": [],
    "latitude": 39.682793,
    "longitude": -105.15446
  },
  {
    "address": "9604 W 25th Pl #B, Lakewood, CO",
    "price": 1700.0,
    "beds": 1.0,
    "baths": 2.0,
    "sqft": 1010.0,
    "year_built": "N/A",
    "description": "",
    "url": "https://www.zillow.com/homedetails/13746912_zpid/",
    "location": "Lakewood, CO",
    "list_date": 2574074000,
    "primary_photo": "https://photos.zillowstatic.com/fp/703001f635f0347b23481e27c2309d6a-p_e.jpg",
    "alt_photos": [],
    "latitude": 39.7538,
    "longitude": -105.10463
  },
  {
    "address": "1556 S Field Ct, Lakewood, CO",
    "price": 2200.0,
    "beds": 2.0,
    "baths": 1.0,
    "sqft": 1013.0,
    "year_built": "N/A",
    "description": "",
    "url": "https://www.zillow.com/homedetails/13783101_zpid/",
    "location": "Lakewood, CO",
    "list_date": 110793000,
    "primary_photo": "https://photos.zillowstatic.com/fp/01ceb581af9e9e9077da281a9868829c-p_e.jpg",
    "alt_photos": [],
    "latitude": 39.6884,
    "longitude": -105.09815
  },
  {
    "address": "7100 W 12th Ave, Lakewood, CO",
    "price": 2650.0,
    "beds": 3.0,
    "baths": 2.0,
    "sqft": 1910.0,
    "year_built": "N/A",
    "description": "",
    "url": "https://www.zillow.com/homedetails/13760533_zpid/",
    "location": "Lakewood, CO",
    "list_date": 368617000,
    "primary_photo": "https://photos.zillowstatic.com/fp/945f531310f60393b6a4065301bab58c-p_e.jpg",
    "alt_photos": [],
    "latitude": 39.734566,
    "longitude": -105.07583
  },
  {
    "address": "136 Yank Way, Denver, CO",
    "price": 2200.0,
    "beds": 2.0,
    "baths": 2.0,
    "sqft": 1100.0,
    "year_built": "N/A",
    "description": "",
    "url": "https://www.zillow.com/homedetails/2060660015_zpid/",
    "location": "Denver, CO",
    "list_date": 324277000,
    "primary_photo": "https://photos.zillowstatic.com/fp/e3ed715037c3789ed504cb397135ee14-p_e.jpg",
    "alt_photos": [],
    "latitude": 39.717773,
    "longitude": -105.14282
  },
  {
    "address": "2352 Garland St, Denver, CO",
    "price": 1685.0,
    "beds": 2.0,
    "baths": 1.0,
    "sqft": 700.0,
    "year_built": "N/A",
    "description": "",
    "url": "https://www.zillow.com/homedetails/2052899708_zpid/",
    "location": "Denver, CO",
    "list_date": 4964182000,
    "primary_photo": "https://photos.zillowstatic.com/fp/b583fca4825e63a7b862cf7964a0b851-p_e.jpg",
    "alt_photos": [],
    "latitude": 39.751072,
    "longitude": -105.10151
  },
  {
    "address": "1460 Ames St, Lakewood, CO",
    "price": 2195.0,
    "beds": 3.0,
    "baths": 1.0,
    "sqft": 1584.0,
    "year_built": "N/A",
    "description": "",
    "url": "https://www.zillow.com/homedetails/13759479_zpid/",
    "location": "Lakewood, CO",
    "list_date": 5448667000,
    "primary_photo": "https://photos.zillowstatic.com/fp/5fcb8d0b029904ae428ba5f3ee2d3a23-p_e.jpg",
    "alt_photos": [],
    "latitude": 39.739647,
    "longitude": -105.05403
  }
]