[
  {
    "address": "5922 Gunbarrel Avenue  Unit E, Boulder, CO",
    "price": 475000.0,
    "beds": 2.0,
    "baths": 2.0,
    "sqft": 1114.0,
    "year_built": "N/A",
    "description": "",
    "url": "https://www.zillow.com/homedetails/446771008_zpid/",
    "location": "Boulder, CO",
    "list_date": 1108879000,
    "primary_photo": "https://photos.zillowstatic.com/fp/9d0cf8b3dbf9c8238be7d28c7acedaa9-p_e.jpg",
    "alt_photos": [],
    "latitude": 40.06073,
    "longitude": -105.21582
  },
  {
    "address": "3054 Fulton Cir, Boulder, CO",
    "price": 499000.0,
    "beds": 2.0,
    "baths": 2.0,
    "sqft": 1032.0,
    "year_built": "N/A",
    "description": "",
    "url": "https://www.zillow.com/homedetails/13235267_zpid/",
    "location": "Boulder, CO",
    "list_date": 8430334000,
    "primary_photo": "https://photos.zillowstatic.com/fp/0fda0320d00896fea5be7c5a4e45178d-p_e.jpg",
    "alt_photos": [],
    "latitude": 40.02975,
    "longitude": -105.24096
  },
  {
    "address": "6168 Habitat Dr, Boulder, CO",
    "price": 499900.0,
    "beds": 3.0,
    "baths": 4.0,
    "sqft": 2274.0,
    "year_built": "N/A",
    "description": "",
    "url": "https://www.zillow.com/homedetails/13241488_zpid/",
    "location": "Boulder, CO",
    "list_date": 3092176000,
    "primary_photo": "https://photos.zillowstatic.com/fp/6f091fb0da259c5d798afc6d58cebb26-p_e.jpg",
    "alt_photos": [],
    "latitude": 40.06088,
    "longitude": -105.21037
  },
  {
    "address": "4853 W Moorhead Cir, Boulder, CO",
    "price": 495000.0,
    "beds": 2.0,
    "baths": 1.0,
    "sqft": 892.0,
    "year_built": "N/A",
    "description": "",
    "url": "https://www.zillow.com/homedetails/13224174_zpid/",
    "location": "Boulder, CO",
    "list_date": 2568855000,
    "primary_photo": "https://photos.zillowstatic.com/fp/78236e5739fedea511a3e521f1f53be6-p_e.jpg",
    "alt_photos": [],
    "latitude": 39.97996,
    "longitude": -105.23626
  },
  {
    "address": "3025 Broadway Street Bldg A  Unit 2, Boulder, CO",
    "price": 485000.0,
    "beds": 2.0,
    "baths": 2.0,
    "sqft": 843.0,
    "year_built": "N/A",
    "description": "",
    "url": "https://www.zillow.com/homedetails/2060475686_zpid/",
    "location": "Boulder, CO",
    "list_date": 1445750000,
    "primary_photo": "https://photos.zillowstatic.com/fp/c7f1cbcb54bd621f95f7299d63a193da-p_e.jpg",
    "alt_photos": [],
    "latitude": 40.029743,
    "longitude": -105.2825
  },
  {
    "address": "2227 Canyon Boulevard  Unit 312a, Boulder, CO",
    "price": 473000.0,
    "beds": 2.0,
    "baths": 2.0,
    "sqft": 1059.0,
    "year_built": "N/A",
    "description": "",
    "url": "https://www.zillow.com/homedetails/13224871_zpid/",
    "location": "Boulder, CO",
    "list_date": 3263164000,
    "primary_photo": "https://photos.zillowstatic.com/fp/ae90b8e25cea3d0401faf8b8011e4f41-p_e.jpg",
    "alt_photos": [],
    "latitude": 40.017757,
    "longitude": -105.26585
  },
  {
    "address": "3805 Northbrook Dr UNIT A, Boulder, CO",
    "price": 459000.0,
    "beds": 2.0,
    "baths": 1.0,
    "sqft": 936.0,
    "year_built": "N/A",
    "description": "",
    "url": "https://www.zillow.com/homedetails/13226700_zpid/",
    "location": "Boulder, CO",
    "list_date": 1191926000,
    "primary_photo": "https://photos.zillowstatic.com/fp/59f1c790a328fc538a3f35f91fec3c07-p_e.jpg",
    "alt_photos": [],
    "latitude": 40.04416,
    "longitude": -105.25963
  },
  {
    "address": "6148 Willow Ln, Boulder, CO",
    "price": 469000.0,
    "beds": 2.0,
    "baths": 2.0,
    "sqft": 1030.0,
    "year_built": "N/A",
    "description": "",
    "url": "https://www.zillow.com/homedetails/13235348_zpid/",
    "location": "Boulder, CO",
    "list_date": 10847718000,
    "primary_photo": "https://photos.zillowstatic.com/fp/80a5470d7ca727b07e54d5155c71628d-p_e.jpg",
    "alt_photos": [],
    "latitude": 40.05977,
    "longitude": -105.21055
  },
  {
    "address": "3727 Talisman Pl UNIT B, Boulder, CO",
    "price": 450000.0,
    "beds": 2.0,
    "baths": 2.0,
    "sqft": 968.0,
    "year_built": "N/A",
    "description": "",
    "url": "https://www.zillow.com/homedetails/13222080_zpid/",
    "location": "Boulder, CO",
    "list_date": 1849113000,
    "primary_photo": "https://photos.zillowstatic.com/fp/d971e91c493af0915943dbf8b53b2286-p_e.jpg",
    "alt_photos": [],
    "latitude": 40.03534,
    "longitude": -105.24691
  },
  {
    "address": "3275 34th St UNIT 77, Boulder, CO",
    "price": 470000.0,
    "beds": 2.0,
    "baths": 1.0,
    "sqft": 930.0,
    "year_built": "N/A",
    "description": "",
    "url": "https://www.zillow.com/homedetails/13233296_zpid/",
    "location": "Boulder, CO",
    "list_date": 483091000,
    "primary_photo": "https://photos.zillowstatic.com/fp/238f8474d1e618d0e049ff567f2b8613-p_e.jpg",
    "alt_photos": [],
    "latitude": 40.03451,
    "longitude": -105.24923
  },
  {
    "address": "1850 Folsom St UNIT 204, Boulder, CO",
    "price": 475000.0,
    "beds": 1.0,
    "baths": 1.0,
    "sqft": 801.0,
    "year_built": "N/A",
    "description": "",
    "url": "https://www.zillow.com/homedetails/13223477_zpid/",
    "location": "Boulder, CO",
    "list_date": 8686338000,
    "primary_photo": "https://photos.zillowstatic.com/fp/e42ca2e407d654bda2950d9fc0fb4064-p_e.jpg",
    "alt_photos": [],
    "latitude": 40.01921,
    "longitude": -105.26235
  },
  {
    "address": "2810 E COLLEGE Ave UNIT 102, Boulder, CO",
    "price": 475000.0,
    "beds": 1.0,
    "baths": 1.0,
    "sqft": 792.0,
    "year_built": "N/A",
    "description": "",
    "url": "https://www.zillow.com/homedetails/90147594_zpid/",
    "location": "Boulder, CO",
    "list_date": 8429378000,
    "primary_photo": "https://photos.zillowstatic.com/fp/d8570e1824ffce4f09f1365fa11def56-p_e.jpg",
    "alt_photos": [],
    "latitude": 40.00707,
    "longitude": -105.25811
  },
  {
    "address": "1111 Maxwell Avenue  Unit 233, Boulder, CO",
    "price": 499950.0,
    "beds": 2.0,
    "baths": 1.0,
    "sqft": 816.0,
    "year_built": "N/A",
    "description": "",
    "url": "https://www.zillow.com/homedetails/13237367_zpid/",
    "location": "Boulder, CO",
    "list_date": 573010000,
    "primary_photo": "https://photos.zillowstatic.com/fp/b3d4da1c1551d87366a52707862431f4-p_e.jpg",
    "alt_photos": [],
    "latitude": 40.021946,
    "longitude": -105.28293
  },
  {
    "address": "1850 Folsom Street  Unit 402, Boulder, CO",
    "price": 500000.0,
    "beds": 1.0,
    "baths": 1.0,
    "sqft": 801.0,
    "year_built": "N/A",
    "description": "",
    "url": "https://www.zillow.com/homedetails/13223499_zpid/",
    "location": "Boulder, CO",
    "list_date": 15171867000,
    "primary_photo": "https://photos.zillowstatic.com/fp/fddd9e68719df61bea2667881581e3e4-p_e.jpg",
    "alt_photos": [],
    "latitude": 40.019196,
    "longitude": -105.26243
  }
]